pylinsql/__init__.py
pylinsql/async_database.py
pylinsql/connection/__init__.py
pylinsql/connection/async_database.py
pylinsql/generator/__init__.py
pylinsql/generator/code_generator.py
pylinsql/generator/conversion.py
pylinsql/generator/database_traits.py
pylinsql/generator/dbml_generator.py
pylinsql/generator/inspection.py
pylinsql/generator/schema.py
pylinsql/generator/sql_generator.py
pylinsql/generator/timing.py
pylinsql/query/__init__.py
pylinsql/query/ast.py
pylinsql/query/base.py
pylinsql/query/builder.py
pylinsql/query/core.py
pylinsql/query/decompiler.py
pylinsql/query/evaluator.py
pylinsql/query/node.py
pylinsql/query/plot.py
pylinsql/query/query.py
pylinsql-0.1.18.dist-info/LICENSE
pylinsql-0.1.18.dist-info/METADATA
pylinsql-0.1.18.dist-info/WHEEL
pylinsql-0.1.18.dist-info/top_level.txt
pylinsql-0.1.18.dist-info/RECORD
