Metadata-Version: 2.1
Name: pylinsql
Version: 0.1.18
Summary: Language-Integrated SQL Queries in Python
Home-page: https://github.com/hunyadi/pylinsql
Author: Levente Hunyadi
Author-email: hunyadi@gmail.com
License: MIT
Classifier: License :: OSI Approved :: MIT License
Classifier: Programming Language :: Python :: 3
Classifier: Programming Language :: Python :: 3.8
Classifier: Programming Language :: Python :: 3.9
Classifier: Programming Language :: Python :: 3.10
Classifier: Development Status :: 7 - Inactive
License-File: LICENSE
Requires-Dist: asyncpg
Requires-Dist: json-strong-typing
